Workbook

Sheet Overview
AA1: Metric | AB1: Amount
B2: AQ COMPANIES | F2: SKY ARIANA LTD | AA2: Total Credits (In) | AB2: =SUM('Account Statement'!F:F)
B3: Corporate Logistics & Banking Portal | Account: 101502******0472 | AA3: Total Debits (Out) | AB3: =SUM('Account Statement'!E:E)
B5: TOTAL AVAILABLE BALANCE | F5: PENDING RECEIVABLES (INVOICED)
B6: =B9 - C9 | F6: =SUMIF('Proforma Invoices'!H:H, "Pending", 'Proforma Invoices'!G:G)
B8: TOTAL CREDITS (IN) | C8: TOTAL DEBITS (OUT) | F8: TOTAL INVOICED (ALL TIME)
B9: =SUM('Account Statement'!F:F) | C9: =SUM('Account Statement'!E:E) | F9: =SUM('Proforma Invoices'!G:G)
B12: LATEST TRANSACTIONS | F12: SYSTEM SHORTCUTS
B13: Date | C13: Description | D13: Amount | F13: Go to Account Statement
B14: =IF(COUNTA('Account Statement'!A:A)>=2, INDEX('Account Statement'!A:A, COUNTA('Account Statement'!A:A)+5-0), "") | C14: =IF(COUNTA('Account Statement'!A:A)>=2, INDEX('Account Statement'!C:C, COUNTA('Account Statement'!A:A)+5-0), "") | D14: =IF(COUNTA('Account Statement'!A:A)>=2, INDEX('Account Statement'!F:F, COUNTA('Account Statement'!A:A)+5-0) - INDEX('Account Statement'!E:E, COUNTA('Account Statement'!A:A)+5-0), "") | F14: Go to Proforma Invoices
B15: =IF(COUNTA('Account Statement'!A:A)>=3, INDEX('Account Statement'!A:A, COUNTA('Account Statement'!A:A)+5-1), "") | C15: =IF(COUNTA('Account Statement'!A:A)>=3, INDEX('Account Statement'!C:C, COUNTA('Account Statement'!A:A)+5-1), "") | D15: =IF(COUNTA('Account Statement'!A:A)>=3, INDEX('Account Statement'!F:F, COUNTA('Account Statement'!A:A)+5-1) - INDEX('Account Statement'!E:E, COUNTA('Account Statement'!A:A)+5-1), "") | F15: Create New Invoice
B16: =IF(COUNTA('Account Statement'!A:A)>=4, INDEX('Account Statement'!A:A, COUNTA('Account Statement'!A:A)+5-2), "") | C16: =IF(COUNTA('Account Statement'!A:A)>=4, INDEX('Account Statement'!C:C, COUNTA('Account Statement'!A:A)+5-2), "") | D16: =IF(COUNTA('Account Statement'!A:A)>=4, INDEX('Account Statement'!F:F, COUNTA('Account Statement'!A:A)+5-2) - INDEX('Account Statement'!E:E, COUNTA('Account Statement'!A:A)+5-2), "") | F16: View Bank Routing Details
B17: =IF(COUNTA('Account Statement'!A:A)>=5, INDEX('Account Statement'!A:A, COUNTA('Account Statement'!A:A)+5-3), "") | C17: =IF(COUNTA('Account Statement'!A:A)>=5, INDEX('Account Statement'!C:C, COUNTA('Account Statement'!A:A)+5-3), "") | D17: =IF(COUNTA('Account Statement'!A:A)>=5, INDEX('Account Statement'!F:F, COUNTA('Account Statement'!A:A)+5-3) - INDEX('Account Statement'!E:E, COUNTA('Account Statement'!A:A)+5-3), "") | F17: Track Active Shipments
B19: CASH FLOW VISUALIZATION
B20: Total Incoming | C20: =B9
B21: Total Outgoing | C21: =C9

Sheet Logistics & Tracking
B2: Shipment & Container Tracking
B3: AQ Companies • Active Freight Logistics
B5: Date | C5: Shipment Ref | D5: Proforma Ref | E5: Container No | F5: B/L Number | G5: Origin -> Destination | H5: Vessel / Carrier | I5: ETA | J5: Status
B6: 10-Oct-2026 | C6: SHP-9001 | D6: 001 | E6: MSKU9023418 | F6: BL-1928374 | G6: Kandahar -> Nhava Sheva | H6: Maersk Line | I6: 22-Oct-2026 | J6: In Transit
B7: 12-Oct-2026 | C7: SHP-9002 | D7: 002 | E7: TGHU8172635 | F7: BL-1928375 | G7: Dogharoun -> Jebel Ali | H7: MSC | I7: 18-Oct-2026 | J7: At Origin Port

Sheet Account & Routing Details
B2: Official Banking Details
B5: Primary USD Account Info
B7: Bank Name: | C7: AFGHAN UNITED BANK
B8: Beneficiary Name: | C8: SKY ARIANA LTD
B9: Account Number (USD): | C9: 101502USD2940472
B10: Bank SWIFT Code: | C10: AFGUAFKAXXX
B13: Correspondent Bank Info (For SWIFT Routing)
B15: Correspondent Bank: | C15: DA AFGHANISTAN BANK
B16: Correspondent SWIFT: | C16: AFGBAFKA

Sheet Account Statement
B2: Transaction History
B3: AQ Companies • Account Statement
H5: Reconciled
A6: Date | B6: Transaction ID / Ref | C6: Description | D6: Category | E6: Debit (USD) | F6: Credit (USD) | G6: Running Balance
A7: 01-Sep-2026 | B7: N/A | C7: Starting Balance Prior to Transfers | D7: Balance | E7: 0 | F7: 83.36 | G7: =SUM($F$5:$F5) - SUM($E$5:$E5)
A8: 30-Sep-2026 | B8: 0464AIR261771143 | C8: Inward Transfer: G.T JAYANTI AGROCHEM (INV 001) | D8: Credit | E8: 0 | F8: 78893.36 | G8: =SUM($F$5:$F6) - SUM($E$5:$E6)
A9: 08-Oct-2026 | B9: 8483AIR261778937 | C9: Inward Transfer: GT INDIA PVT LTD | D9: Credit | E9: 0 | F9: 74376.25 | G9: =SUM($F$5:$F7) - SUM($E$5:$E7)
A10: 08-Oct-2026 | B10: N/A | C10: Payment to Hayatullah Noori | D10: Debit | E10: 15200 | F10: 0 | G10: =SUM($F$5:$F8) - SUM($E$5:$E8)
A11: 08-Oct-2026 | B11: AD 5708262 | C11: Payment to Sodiqjon Aminov (Tashkent) | D11: Debit | E11: 35000 | F11: 0 | G11: =SUM($F$5:$F9) - SUM($E$5:$E9)
A12: 08-Oct-2026 | B12: N/A | C12: Payment to NAJEB AMIN LTD | D12: Debit | E12: 78893.36 | F12: 0 | G12: =SUM($F$5:$F10) - SUM($E$5:$E10)

Sheet Invoice Generator
B2: PROFORMA INVOICE | F2: Date:
B3: SKY ARIANA LTD | F3: Proforma No:
B4: info@skyariana.com | www.skyariana.com | F4: Payment Terms: | G4: 100% Advance Payment
B6: BILL TO / CONSIGNEE:
B7: [Enter Company Name]
B8: [Enter Address Line 1]
B9: [Enter Address Line 2]
B12: Item Description | E12: Total Net Wt (KG) | F12: C&F Unit Price (USD) | G12: Total Amount (USD)
G13: =IF(ISBLANK(E13), "", E13*F13)
G14: =IF(ISBLANK(E14), "", E14*F14)
G15: =IF(ISBLANK(E15), "", E15*F15)
G16: =IF(ISBLANK(E16), "", E16*F16)
G17: =IF(ISBLANK(E17), "", E17*F17)
G18: =IF(ISBLANK(E18), "", E18*F18)
G19: =IF(ISBLANK(E19), "", E19*F19)
G20: =IF(ISBLANK(E20), "", E20*F20)
G21: =IF(ISBLANK(E21), "", E21*F21)
G22: =IF(ISBLANK(E22), "", E22*F22)
F24: GRAND TOTAL: | G24: =SUM(G13:G22)
B26: BANKING DETAILS FOR PAYMENT
B28: Bank Name: | D28: ='Account & Routing Details'!C7
B29: Beneficiary Name: | D29: ='Account & Routing Details'!C8
B30: Account No (USD): | D30: ='Account & Routing Details'!C9
B31: SWIFT Code: | D31: ='Account & Routing Details'!C10
B32: Correspondent Bank: | D32: ='Account & Routing Details'!C15 | G32: Authorized Signature
B33: Correspondent SWIFT: | D33: ='Account & Routing Details'!C16

Sheet Proforma Invoices
B2: Receivables & Invoices
B3: AQ Companies • Proforma Tracking
B6: Invoice Date | C6: Proforma No | D6: Buyer / Consignee | E6: Item Description | F6: Total Net Wt (KG) | G6: Expected Amount (USD) | H6: Payment Status
B7: 05-Sep-2026 | C7: 001 | D7: G.T JAYANTI AGROCHEM INDIA PVT LTD | E7: Black Raisins (Best) - 1,385 CTNS | F7: 22160 | G7: 79332.8 | H7: PAID (See Ledger)
B8: 23-Sep-2026 | C8: 001 | D8: G.T INDIA PVT LTD | E8: Black Raisins - 2,300 CTNS | F8: 23000 | G8: 74750 | H8: PAID (See Ledger)
B9: 23-Sep-2026 | C9: 002 | D9: G.T INDIA PVT LTD | E9: Black Raisins - 2,295 CTNS | F9: 22950 | G9: 74587.5 | H9: Pending
B10: 23-Sep-2026 | C10: 002 | D10: G.T JAYANTI AGROCHEM INDIA PVT LTD | E10: Black Raisins - 2,250 CTNS | F10: 22500 | G10: 63000 | H10: Pending
B11: 28-Sep-2026 | C11: 001 | D11: MANIK TRADERS | E11: Black Raisins - 1,383 CTNS | F11: 22128 | G11: 57533 | H11: Pending
B12: 28-Sep-2026 | C12: 002 | D12: MANIK TRADERS | E12: Black Raisins - 1,384 CTNS | F12: 22144 | G12: 62003 | H12: Pending
B13: 28-Sep-2026 | C13: 003 | D13: MANIK TRADERS | E13: Black Raisins - 1,385 CTNS | F13: 22160 | G13: 72020 | H13: Pending
B14: 28-Sep-2026 | C14: 001 | D14: SPDC BITES LLP | E14: Black Raisins - 1,382 CTNS | F14: 22122 | G14: 71864 | H14: Pending
